{"assets":[],"ddd":0,"fr":30,"h":500,"ip":0,"layers":[{"ddd":0,"ind":1,"ty":4,"nm":"만족도","hd":false,"sr":1,"ks":{"a":{"a":0,"k":[0,0]},"o":{"a":1,"k":[{"t":0,"s":[100],"i":{"x":0.75,"y":0.75},"o":{"x":0.25,"y":0.25}},{"t":15,"s":[0],"i":{"x":0.75,"y":0.75},"o":{"x":0.25,"y":0.25}},{"t":24,"s":[100],"i":{"x":0,"y":0},"o":{"x":1,"y":1}}]},"p":{"a":0,"k":[184.427,133.841]},"r":{"a":0,"k":0},"s":{"a":1,"k":[{"t":0,"s":[0,0],"i":{"x":0.15,"y":1.35},"o":{"x":0.15,"y":0.45}},{"t":22.5,"s":[0,0],"i":{"x":0.15,"y":1.35},"o":{"x":0.15,"y":0.45}},{"t":35.4,"s":[100,100],"i":{"x":0.88,"y":0.77},"o":{"x":0.5,"y":0}},{"t":145.8,"s":[100,100],"i":{"x":0.5,"y":1},"o":{"x":0.12,"y":0.23}},{"t":153,"s":[0,0],"i":{"x":0,"y":0},"o":{"x":1,"y":1}}]},"sk":{"a":0,"k":0},"sa":{"a":0,"k":0}},"ao":0,"ip":0,"op":181,"st":0,"bm":0,"shapes":[{"ty":"gr","hd":false,"nm":"Group 4 Group","bm":0,"it":[{"ty":"gr","hd":false,"nm":"Group 3 Group","bm":0,"it":[{"ty":"gr","hd":false,"nm":"Path 1 Group","bm":0,"it":[{"ty":"sh","hd":false,"nm":"Path 1","d":1,"ks":{"a":0,"k":{"c":true,"i":[[0,0],[0.573,0],[0,0.573],[-0.573,0],[0,-0.573]],"o":[[0,0.573],[-0.573,0],[0,-0.573],[0.573,0],[0,0]],"v":[[167.323,130.961],[166.286,131.998],[165.249,130.961],[166.286,129.924],[167.323,130.961]]}}},{"ty":"fl","hd":false,"bm":0,"c":{"a":0,"k":[1,1,1]},"r":1,"o":{"a":0,"k":100}},{"ty":"tr","nm":"Transform","a":{"a":0,"k":[0,0]},"o":{"a":0,"k":100},"p":{"a":0,"k":[-163.175,-133.035]},"r":{"a":0,"k":0},"s":{"a":0,"k":[100,100]},"sk":{"a":0,"k":0},"sa":{"a":0,"k":0}}],"np":0},{"ty":"gr","hd":false,"nm":"Path 1 Group","bm":0,"it":[{"ty":"sh","hd":false,"nm":"Path 1","d":1,"ks":{"a":0,"k":{"c":true,"i":[[0,0],[0.573,0],[0,0.573],[-0.573,0],[0,-0.573]],"o":[[0,0.573],[-0.573,0],[0,-0.573],[0.573,0],[0,0]],"v":[[161.099,130.961],[160.062,131.998],[159.025,130.961],[160.062,129.924],[161.099,130.961]]}}},{"ty":"fl","hd":false,"bm":0,"c":{"a":0,"k":[1,1,1]},"r":1,"o":{"a":0,"k":100}},{"ty":"tr","nm":"Transform","a":{"a":0,"k":[0,0]},"o":{"a":0,"k":100},"p":{"a":0,"k":[-163.175,-133.035]},"r":{"a":0,"k":0},"s":{"a":0,"k":[100,100]},"sk":{"a":0,"k":0},"sa":{"a":0,"k":0}}],"np":0},{"ty":"gr","hd":false,"nm":"Path 1 Group","bm":0,"it":[{"ty":"sh","hd":false,"nm":"Path 1","d":1,"ks":{"a":0,"k":{"c":false,"i":[[0,0],[-0.107,-0.266],[0,0],[0,0],[0,0],[0,0],[-0.015,-0.028],[-0.067,-0.105],[-0.316,-0.287],[-1.678,0],[-0.625,0.568],[-0.134,0.212],[-0.028,0.057],[-0.005,0.013],[0,0],[-0.232,-0.325],[0.056,-0.159],[0,0],[0,0],[0,0],[0,0],[0,0],[0,0],[0.021,-0.043],[0.07,-0.11],[0.323,-0.294],[1.953,0],[0.802,0.729],[0.236,0.368],[0.071,0.152],[0,0],[0,0],[0,0],[0,0],[0,0],[0,0],[-0.265,0.107]],"o":[[0.266,-0.106],[0,0],[0,0],[0,0],[0,0],[0.005,0.013],[0.028,0.057],[0.134,0.212],[0.625,0.568],[1.678,0],[0.316,-0.287],[0.067,-0.105],[0.015,-0.028],[0,0],[0.166,-0.363],[0.098,0.137],[0,0],[0,0],[0,0],[0,0],[0,0],[0,0],[-0.011,0.026],[-0.059,0.116],[-0.236,0.368],[-0.802,0.729],[-1.953,0],[-0.323,-0.294],[-0.09,-0.142],[0,0],[0,0],[0,0],[0,0],[0,0],[0,0],[-0.106,-0.266],[0,0]],"v":[[158.312,133.592],[158.987,133.881],[158.505,134.074],[158.987,133.881],[158.986,133.88],[158.991,133.891],[159.021,133.953],[159.162,134.201],[159.826,134.986],[163.173,136.148],[166.52,134.986],[167.184,134.201],[167.325,133.953],[167.355,133.891],[167.36,133.879],[168.255,133.793],[168.322,134.266],[167.841,134.074],[168.322,134.266],[168.321,134.269],[168.32,134.273],[168.316,134.283],[168.302,134.314],[168.253,134.417],[168.06,134.756],[167.217,135.754],[163.173,137.186],[159.129,135.754],[158.286,134.756],[158.044,134.314],[158.03,134.283],[158.026,134.273],[158.025,134.269],[158.024,134.267],[158.505,134.074],[158.024,134.266],[158.312,133.592]]}}},{"ty":"fl","hd":false,"bm":0,"c":{"a":0,"k":[1,1,1]},"r":1,"o":{"a":0,"k":100}},{"ty":"tr","nm":"Transform","a":{"a":0,"k":[0,0]},"o":{"a":0,"k":100},"p":{"a":0,"k":[-163.175,-133.035]},"r":{"a":0,"k":0},"s":{"a":0,"k":[100,100]},"sk":{"a":0,"k":0},"sa":{"a":0,"k":0}}],"np":0},{"ty":"gr","hd":false,"nm":"Path 1 Group","bm":0,"it":[{"ty":"sh","hd":false,"nm":"Path 1","d":1,"ks":{"a":0,"k":{"c":true,"i":[[0,0],[6.302,0],[0,6.302],[-6.302,0],[0,-6.302]],"o":[[0,6.302],[-6.302,0],[0,-6.302],[6.302,0],[0,0]],"v":[[174.585,133.035],[163.175,144.445],[151.765,133.035],[163.175,121.625],[174.585,133.035]]}}},{"ty":"fl","hd":false,"bm":0,"c":{"a":0,"k":[0.424,0.612,0.98]},"r":1,"o":{"a":0,"k":100}},{"ty":"tr","nm":"Transform","a":{"a":0,"k":[0,0]},"o":{"a":0,"k":100},"p":{"a":0,"k":[-163.175,-133.035]},"r":{"a":0,"k":0},"s":{"a":0,"k":[100,100]},"sk":{"a":0,"k":0},"sa":{"a":0,"k":0}}],"np":0},{"ty":"tr","nm":"Transform","a":{"a":0,"k":[0,0]},"o":{"a":0,"k":100},"p":{"a":0,"k":[-21.792,0]},"r":{"a":0,"k":0},"s":{"a":0,"k":[100,100]},"sk":{"a":0,"k":0},"sa":{"a":0,"k":0}}],"np":0},{"ty":"gr","hd":false,"nm":"Path 1 (7) Group","bm":0,"it":[{"ty":"sh","hd":false,"nm":"Path 1 (7)","d":1,"ks":{"a":0,"k":{"c":false,"i":[[0,0],[-0.01,2.182],[-2.034,-0.01],[-0.01,-2.201],[2.089,0.009]],"o":[[-2.09,0.009],[-0.01,-2.201],[2.117,-0.01],[-0.01,2.21],[0,0]],"v":[[205.564,132.84],[202.351,129.144],[205.564,125.43],[208.814,129.144],[205.564,132.84]]}}},{"ty":"sh","hd":false,"nm":"Path 1 (7)","d":1,"ks":{"a":0,"k":{"c":false,"i":[[0,0],[-0.725,0],[-0.01,1.133],[0.807,-0.01],[-0.01,-1.105]],"o":[[-0.01,1.133],[0.78,0],[-0.01,-1.124],[-0.753,0],[0,0]],"v":[[204.431,129.144],[205.564,131.02],[206.734,129.144],[205.564,127.25],[204.431,129.144]]}}},{"ty":"sh","hd":false,"nm":"Path 1 (7)","d":1,"ks":{"a":0,"k":{"c":true,"i":[[0,0],[-0.251,0.435],[-0.01,0.014],[0,0],[-0.215,-0.001],[0,0],[0.298,-0.434],[0,0],[0.215,0.001]],"o":[[-0.503,0],[0.009,-0.015],[0,0],[0.121,-0.178],[0,0],[0.526,0],[0,0],[-0.121,0.178],[0,0]],"v":[[205.71,139.414],[205.145,138.434],[205.172,138.391],[213.522,126.251],[214.06,125.968],[214.74,125.968],[215.278,126.992],[206.928,139.131],[206.39,139.414]]}}},{"ty":"sh","hd":false,"nm":"Path 1 (7)","d":1,"ks":{"a":0,"k":{"c":false,"i":[[0,0],[-2.043,-0.009],[0,-2.2],[2.08,-0.01],[-0.009,2.183]],"o":[[-0.009,-2.2],[2.108,-0.009],[0,2.21],[-2.089,-0.01],[0,0]],"v":[[211.729,136.238],[214.942,132.524],[218.174,136.238],[214.942,139.953],[211.729,136.238]]}}},{"ty":"sh","hd":false,"nm":"Path 1 (7)","d":1,"ks":{"a":0,"k":{"c":false,"i":[[0,0],[-0.733,0],[-0.009,1.133],[0.808,-0.009],[0.009,-1.105]],"o":[[0.009,1.133],[0.771,0],[-0.009,-1.123],[-0.752,0],[0,0]],"v":[[213.791,136.238],[214.942,138.114],[216.112,136.238],[214.942,134.344],[213.791,136.238]]}}},{"ty":"sh","hd":false,"nm":"Path 1 (7)","d":1,"ks":{"a":0,"k":{"c":false,"i":[[0,0],[0.31,2.131],[-0.274,0],[0,0],[-0.085,-0.247],[-0.917,0.008],[0.01,1.31],[1.291,0],[0.38,-0.548],[0.185,-0.007],[0,0],[-0.024,0.286],[0,0],[-0.254,0],[0,0],[0,-0.271],[0,0],[0.271,0],[0,0],[0.025,-0.251],[0,0],[-0.033,0],[-0.011,0.018],[-1.239,-0.01],[0,-2.563],[3.129,0]],"o":[[-2.735,0],[-0.039,-0.272],[0,0],[0.262,0],[0.253,0.735],[1.263,0.009],[0.01,-1.309],[-0.834,0],[-0.101,0.155],[0,0],[-0.287,0],[0,0],[0.022,-0.253],[0,0],[0.271,0],[0,0],[0,0.271],[0,0],[-0.252,0],[0,0],[-0.004,0.033],[0.021,0],[0.464,-0.72],[2.442,-0.01],[0,2.767],[0,0]],"v":[[194.827,139.6],[189.76,135.994],[190.219,135.496],[192.335,135.496],[192.889,135.954],[194.827,137.149],[196.981,134.957],[194.79,132.747],[192.975,133.585],[192.52,133.843],[190.513,133.843],[190.025,133.312],[190.61,126.417],[191.098,125.969],[198.757,125.969],[199.247,126.459],[199.247,128.042],[198.757,128.532],[193.692,128.532],[193.205,128.974],[192.939,131.683],[192.994,131.745],[193.042,131.718],[195.793,130.482],[200.046,134.865],[194.827,139.6]]}}},{"ty":"sh","hd":false,"nm":"Path 1 (7)","d":1,"ks":{"a":0,"k":{"c":true,"i":[[0,0],[-0.167,0.326],[0,0],[-0.001,0.012],[0.041,0],[0,0],[0,0.271],[0,0],[-0.271,0],[0,0],[0,-0.271],[0,0],[0.035,-0.069],[0,0],[0.185,0]],"o":[[-0.366,0.001],[0,0],[0.005,-0.011],[0.001,-0.041],[0,0],[-0.271,0],[0,0],[0,-0.271],[0,0],[0.27,0],[0,0],[0,0.077],[0,0],[-0.084,0.164],[0,0]],"v":[[180.12,139.415],[179.683,138.702],[184.809,128.641],[184.817,128.607],[184.743,128.532],[178.882,128.532],[178.392,128.042],[178.392,126.459],[178.882,125.969],[187.615,125.969],[188.105,126.459],[188.105,128.433],[188.052,128.655],[182.725,139.147],[182.288,139.415]]}}},{"ty":"fl","hd":false,"bm":0,"c":{"a":0,"k":[0.255,0.369,0.588]},"r":1,"o":{"a":0,"k":100}},{"ty":"tr","nm":"Transform","a":{"a":0,"k":[0,0]},"o":{"a":0,"k":100},"p":{"a":0,"k":[-184.972,-132]},"r":{"a":0,"k":0},"s":{"a":0,"k":[100,100]},"sk":{"a":0,"k":0},"sa":{"a":0,"k":0}}],"np":0},{"ty":"tr","nm":"Transform","a":{"a":0,"k":[0,0]},"o":{"a":0,"k":100},"p":{"a":0,"k":[0.543,0.159]},"r":{"a":0,"k":0},"s":{"a":0,"k":[100,100]},"sk":{"a":0,"k":0},"sa":{"a":0,"k":0}}],"np":0},{"ty":"gr","hd":false,"nm":"Path 1 Group","bm":0,"it":[{"ty":"sh","hd":false,"nm":"Path 1","d":1,"ks":{"a":0,"k":{"c":true,"i":[[0,0],[0,0],[0,-9.453],[0,0],[9.453,0],[0,0],[0,9.453],[0,0],[-9.453,0]],"o":[[0,0],[9.453,0],[0,0],[0,9.453],[0,0],[-9.453,0],[0,0],[0,-9.453],[0,0]],"v":[[157.452,116.726],[211.403,116.726],[228.519,133.841],[228.519,133.841],[211.403,150.957],[157.452,150.957],[140.336,133.841],[140.336,133.841],[157.452,116.726]]}}},{"ty":"fl","hd":false,"bm":0,"c":{"a":0,"k":[1,1,1]},"r":1,"o":{"a":0,"k":100}},{"ty":"tr","nm":"Transform","a":{"a":0,"k":[0,0]},"o":{"a":0,"k":100},"p":{"a":0,"k":[-184.427,-133.841]},"r":{"a":0,"k":0},"s":{"a":0,"k":[100,100]},"sk":{"a":0,"k":0},"sa":{"a":0,"k":0}}],"np":0}]},{"ddd":0,"ind":10,"ty":4,"nm":"성취율","hd":false,"sr":1,"ks":{"a":{"a":0,"k":[0,0]},"o":{"a":0,"k":100},"p":{"a":0,"k":[324.828,310.269]},"r":{"a":0,"k":0},"s":{"a":1,"k":[{"t":0,"s":[0,0],"i":{"x":0.75,"y":0.75},"o":{"x":0.25,"y":0.25}},{"t":84.6,"s":[0,0],"i":{"x":0.15,"y":1.35},"o":{"x":0.15,"y":0.45}},{"t":93.6,"s":[100,100],"i":{"x":0.15,"y":1.35},"o":{"x":0.15,"y":0.45}},{"t":147,"s":[100,100],"i":{"x":0.5,"y":1},"o":{"x":0.12,"y":0.23}},{"t":153,"s":[0,0],"i":{"x":0,"y":0},"o":{"x":1,"y":1}}]},"sk":{"a":0,"k":0},"sa":{"a":0,"k":0}},"ao":0,"ip":0,"op":181,"st":0,"bm":0,"shapes":[{"ty":"gr","hd":false,"nm":"Group 5 Group","bm":0,"it":[{"ty":"gr","hd":false,"nm":"Path 1 Group","bm":0,"it":[{"ty":"sh","hd":false,"nm":"Path 1","d":1,"ks":{"a":0,"k":{"c":true,"i":[[0,0],[0.629,1.088],[0,0],[0,0],[0,0]],"o":[[-0.628,1.089],[0,0],[0,0],[0,0],[0,0]],"v":[[325.218,332.111],[322.39,332.112],[322.389,332.111],[314.611,318.639],[332.996,318.639]]}}},{"ty":"fl","hd":false,"bm":0,"c":{"a":0,"k":[1,1,1]},"r":1,"o":{"a":0,"k":100}},{"ty":"tr","nm":"Transform","a":{"a":0,"k":[0,0]},"o":{"a":0,"k":100},"p":{"a":0,"k":[-324.828,-310.269]},"r":{"a":0,"k":0},"s":{"a":0,"k":[100,100]},"sk":{"a":0,"k":0},"sa":{"a":0,"k":0}}],"np":0},{"ty":"gr","hd":false,"nm":"Path 1 Group","bm":0,"it":[{"ty":"sh","hd":false,"nm":"Path 1","d":1,"ks":{"a":0,"k":{"c":false,"i":[[0,0],[4.083,-3.279],[-4.151,-4.348],[-1.345,-0.506],[0,0],[0,0],[0,0],[0,0],[-2.124,2.098],[1.42,1.394],[1.296,-1.977]],"o":[[-1.295,-1.977],[-1.42,1.394],[2.124,2.098],[0,0],[0,0],[0,0],[0,0],[1.345,-0.506],[4.151,-4.348],[-4.083,-3.279],[0,0]],"v":[[302.785,299.023],[293.808,297.206],[294.737,306.822],[302.78,313.736],[302.78,313.74],[302.785,313.738],[302.791,313.74],[302.791,313.736],[310.834,306.822],[311.763,297.206],[302.785,299.023]]}}},{"ty":"fl","hd":false,"bm":0,"c":{"a":0,"k":[0.424,0.612,0.98]},"r":1,"o":{"a":0,"k":100}},{"ty":"tr","nm":"Transform","a":{"a":0,"k":[0,0]},"o":{"a":0,"k":100},"p":{"a":0,"k":[-324.828,-310.269]},"r":{"a":0,"k":0},"s":{"a":0,"k":[100,100]},"sk":{"a":0,"k":0},"sa":{"a":0,"k":0}}],"np":0},{"ty":"gr","hd":false,"nm":"Path 1 (10) Group","bm":0,"it":[{"ty":"sh","hd":false,"nm":"Path 1 (10)","d":1,"ks":{"a":0,"k":{"c":false,"i":[[0,0],[-0.009,2.183],[-2.034,-0.009],[-0.009,-2.2],[2.089,0.01]],"o":[[-2.089,0.01],[-0.009,-2.2],[2.117,-0.009],[-0.009,2.211],[0,0]],"v":[[343.503,304.822],[340.29,301.126],[343.503,297.412],[346.753,301.126],[343.503,304.822]]}}},{"ty":"sh","hd":false,"nm":"Path 1 (10)","d":1,"ks":{"a":0,"k":{"c":false,"i":[[0,0],[-0.724,0],[-0.009,1.133],[0.808,-0.009],[-0.009,-1.105]],"o":[[-0.009,1.133],[0.78,0],[-0.009,-1.123],[-0.752,0],[0,0]],"v":[[342.37,301.126],[343.503,303.002],[344.673,301.126],[343.503,299.232],[342.37,301.126]]}}},{"ty":"sh","hd":false,"nm":"Path 1 (10)","d":1,"ks":{"a":0,"k":{"c":true,"i":[[0,0],[-0.253,0.436],[-0.009,0.014],[0,0],[-0.215,0],[0,0],[0.298,-0.433],[0,0],[0.215,0.001]],"o":[[-0.503,-0.001],[0.008,-0.014],[0,0],[0.121,-0.178],[0,0],[0.526,0],[0,0],[-0.122,0.178],[0,0]],"v":[[343.649,311.397],[343.085,310.415],[343.111,310.373],[351.461,298.234],[351.999,297.951],[352.68,297.951],[353.218,298.974],[344.868,311.114],[344.329,311.397]]}}},{"ty":"sh","hd":false,"nm":"Path 1 (10)","d":1,"ks":{"a":0,"k":{"c":false,"i":[[0,0],[-2.043,-0.01],[0,-2.201],[2.08,-0.009],[-0.01,2.182]],"o":[[-0.01,-2.201],[2.108,-0.01],[0,2.21],[-2.09,-0.009],[0,0]],"v":[[349.669,308.221],[352.882,304.507],[356.113,308.221],[352.882,311.935],[349.669,308.221]]}}},{"ty":"sh","hd":false,"nm":"Path 1 (10)","d":1,"ks":{"a":0,"k":{"c":false,"i":[[0,0],[-0.734,0],[-0.01,1.133],[0.808,-0.01],[0.01,-1.105]],"o":[[0.01,1.133],[0.77,0],[-0.01,-1.124],[-0.752,0],[0,0]],"v":[[351.73,308.221],[352.882,310.097],[354.052,308.221],[352.882,306.327],[351.73,308.221]]}}},{"ty":"sh","hd":false,"nm":"Path 1 (10)","d":1,"ks":{"a":0,"k":{"c":false,"i":[[0,0],[0.715,1.238],[0,2.29],[-0.708,1.244],[-1.767,0],[-0.715,-1.244],[0,-2.29],[0.714,-1.237],[1.767,0]],"o":[[-1.767,0],[-0.708,-1.237],[0,-2.29],[0.715,-1.244],[1.767,0],[0.708,1.244],[0,2.29],[-0.708,1.238],[0,0]],"v":[[332.452,312.015],[328.73,310.158],[327.668,304.867],[328.73,299.566],[332.452,297.7],[336.174,299.566],[337.236,304.867],[336.165,310.158],[332.452,312.015]]}}},{"ty":"sh","hd":false,"nm":"Path 1 (10)","d":1,"ks":{"a":0,"k":{"c":false,"i":[[0,0],[0,1.595],[0.255,0.804],[0.81,0],[0.261,-0.803],[0,-1.671],[-0.262,-0.849],[-0.81,0],[-0.255,0.849]],"o":[[0.249,-0.842],[0,-1.671],[-0.249,-0.803],[-0.81,0],[-0.262,0.804],[0,1.595],[0.261,0.842],[0.81,0],[0,0]],"v":[[334.05,308.522],[334.423,304.867],[334.041,301.154],[332.452,299.949],[330.845,301.154],[330.452,304.867],[330.845,308.532],[332.452,309.795],[334.05,308.522]]}}},{"ty":"sh","hd":false,"nm":"Path 1 (10)","d":1,"ks":{"a":0,"k":{"c":false,"i":[[0,0],[0,1.167],[-0.351,0.631],[-0.658,0.298],[0.204,0.517],[0,0.453],[-0.759,0.708],[-1.384,0],[-0.759,-0.715],[0,-1.008],[0.204,-0.523],[0.67,-0.383],[-0.345,-0.632],[0,-0.778],[0.867,-0.823],[1.55,0],[0.797,0.823]],"o":[[-0.797,-0.817],[0,-0.778],[0.355,-0.629],[-0.67,-0.447],[-0.198,-0.523],[0,-1.008],[0.759,-0.715],[1.384,0],[0.759,0.708],[0,0.453],[-0.198,0.517],[0.683,0.383],[0.344,0.631],[0,1.168],[-0.861,0.816],[-1.55,0],[0,0]],"v":[[317.861,310.8],[316.665,307.824],[317.191,305.71],[318.751,304.284],[317.44,302.839],[317.143,301.375],[318.282,298.801],[321.497,297.729],[324.712,298.801],[325.851,301.375],[325.545,302.839],[324.243,304.188],[325.784,305.71],[326.3,307.824],[324.999,310.81],[321.382,312.034],[317.861,310.8]]}}},{"ty":"sh","hd":false,"nm":"Path 1 (10)","d":1,"ks":{"a":0,"k":{"c":false,"i":[[0,0],[-0.351,-0.377],[-0.625,0],[-0.351,0.376],[0,0.683],[0.363,0.363],[0.612,0],[0.364,-0.37],[0,-0.707]],"o":[[0,0.683],[0.357,0.376],[0.625,0],[0.357,-0.377],[0,-0.708],[-0.358,-0.37],[-0.612,0],[-0.357,0.364],[0,0]],"v":[[319.497,307.642],[320.024,309.231],[321.497,309.795],[322.961,309.231],[323.497,307.642],[322.952,306.035],[321.497,305.48],[320.033,306.035],[319.497,307.642]]}}},{"ty":"sh","hd":false,"nm":"Path 1 (10)","d":1,"ks":{"a":0,"k":{"c":false,"i":[[0,0],[-0.548,0],[-0.3,0.319],[0,0.504],[0.307,0.306],[0.555,0],[0.313,-0.313],[0,-0.548],[-0.313,-0.319]],"o":[[0.307,0.319],[0.555,0],[0.307,-0.319],[0,-0.549],[-0.3,-0.313],[-0.548,0],[-0.306,0.307],[0,0.504],[0,0]],"v":[[320.215,302.916],[321.497,303.394],[322.779,302.916],[323.239,301.681],[322.779,300.399],[321.497,299.93],[320.205,300.399],[319.746,301.681],[320.215,302.916]]}}},{"ty":"fl","hd":false,"bm":0,"c":{"a":0,"k":[0.255,0.369,0.588]},"r":1,"o":{"a":0,"k":100}},{"ty":"tr","nm":"Transform","a":{"a":0,"k":[0,0]},"o":{"a":0,"k":100},"p":{"a":0,"k":[-324.828,-310.269]},"r":{"a":0,"k":0},"s":{"a":0,"k":[100,100]},"sk":{"a":0,"k":0},"sa":{"a":0,"k":0}}],"np":0},{"ty":"gr","hd":false,"nm":"Path 1 Group","bm":0,"it":[{"ty":"sh","hd":false,"nm":"Path 1","d":1,"ks":{"a":0,"k":{"c":true,"i":[[0,0],[0,0],[0,-9.453],[0,0],[9.453,0],[0,0],[0,9.453],[0,0],[-9.453,0]],"o":[[0,0],[9.453,0],[0,0],[0,9.453],[0,0],[-9.453,0],[0,0],[0,-9.453],[0,0]],"v":[[297.853,287.611],[351.804,287.611],[368.92,304.727],[368.92,304.727],[351.804,321.842],[297.853,321.842],[280.737,304.727],[280.737,304.727],[297.853,287.611]]}}},{"ty":"fl","hd":false,"bm":0,"c":{"a":0,"k":[1,1,1]},"r":1,"o":{"a":0,"k":100}},{"ty":"tr","nm":"Transform","a":{"a":0,"k":[0,0]},"o":{"a":0,"k":100},"p":{"a":0,"k":[-324.828,-310.269]},"r":{"a":0,"k":0},"s":{"a":0,"k":[100,100]},"sk":{"a":0,"k":0},"sa":{"a":0,"k":0}}],"np":0},{"ty":"tr","nm":"Transform","a":{"a":0,"k":[0,0]},"o":{"a":0,"k":100},"p":{"a":0,"k":[0,0]},"r":{"a":0,"k":0},"s":{"a":0,"k":[100,100]},"sk":{"a":0,"k":0},"sa":{"a":0,"k":0}}],"np":0}]},{"ddd":0,"ind":16,"ty":4,"nm":"막대그래프","hd":false,"sr":1,"ks":{"a":{"a":0,"k":[0,0]},"o":{"a":1,"k":[{"t":0,"s":[0],"i":{"x":0.75,"y":0.75},"o":{"x":0.25,"y":0.25}},{"t":44.4,"s":[0],"i":{"x":0.15,"y":1.35},"o":{"x":0.15,"y":0.45}},{"t":66.9,"s":[100],"i":{"x":0.15,"y":1.35},"o":{"x":0.15,"y":0.45}},{"t":147,"s":[100],"i":{"x":0.5,"y":1},"o":{"x":0.12,"y":0.23}},{"t":153,"s":[0],"i":{"x":0,"y":0},"o":{"x":1,"y":1}}]},"p":{"a":0,"k":[249.777,357.423]},"r":{"a":0,"k":0},"s":{"a":0,"k":[100,100]},"sk":{"a":0,"k":0},"sa":{"a":0,"k":0}},"ao":0,"ip":0,"op":181,"st":0,"bm":0,"shapes":[{"ty":"gr","hd":false,"nm":"1 Group","bm":0,"it":[{"ty":"sh","hd":false,"nm":"1","d":1,"ks":{"a":0,"k":{"c":false,"i":[[0,0],[-9.019,0],[0,0],[0,1.105],[0,0],[1.105,0],[0,0],[0,-9.018]],"o":[[0,9.019],[0,0],[1.105,0],[0,0],[0,-1.105],[0,0],[-9.019,0],[0,0]],"v":[[129.5,357.422],[145.83,373.752],[172.257,373.752],[174.257,371.752],[174.257,343.093],[172.257,341.093],[145.83,341.093],[129.5,357.422]]}}},{"ty":"fl","hd":false,"bm":0,"c":{"a":1,"k":[{"t":0,"s":[0.424,0.612,0.98],"i":{"x":0.75,"y":0.75},"o":{"x":0.25,"y":0.25}},{"t":66.9,"s":[0.255,0.369,0.588],"i":{"x":0.88,"y":0.77},"o":{"x":0.5,"y":0}},{"t":71.4,"s":[0.424,0.612,0.98],"i":{"x":0,"y":0},"o":{"x":1,"y":1}}]},"r":1,"o":{"a":0,"k":100}},{"ty":"tr","nm":"Transform","a":{"a":0,"k":[0,0]},"o":{"a":0,"k":100},"p":{"a":0,"k":[-249.777,-357.422]},"r":{"a":0,"k":0},"s":{"a":0,"k":[100,100]},"sk":{"a":0,"k":0},"sa":{"a":0,"k":0}}],"np":0},{"ty":"gr","hd":false,"nm":"2 Group","bm":0,"it":[{"ty":"sh","hd":false,"nm":"2","d":1,"ks":{"a":0,"k":{"c":true,"i":[[0,0],[0,0],[0,-1.105],[0,0],[1.105,0],[0,0],[0,1.105],[0,0],[-1.105,0]],"o":[[0,0],[1.105,0],[0,0],[0,1.105],[0,0],[-1.105,0],[0,0],[0,-1.105],[0,0]],"v":[[2,0],[44.547,0],[46.547,2],[46.547,30.659],[44.547,32.659],[2,32.659],[0,30.659],[0,2],[2,0]]}}},{"ty":"fl","hd":false,"bm":0,"c":{"a":1,"k":[{"t":0,"s":[0.424,0.612,0.98],"i":{"x":0.75,"y":0.75},"o":{"x":0.25,"y":0.25}},{"t":71.4,"s":[0.255,0.369,0.588],"i":{"x":0.88,"y":0.77},"o":{"x":0.5,"y":0}},{"t":75.6,"s":[0.424,0.612,0.98],"i":{"x":0,"y":0},"o":{"x":1,"y":1}}]},"r":1,"o":{"a":0,"k":100}},{"ty":"tr","nm":"Transform","a":{"a":0,"k":[0,0]},"o":{"a":0,"k":100},"p":{"a":0,"k":[-72.573,16.33]},"r":{"a":0,"k":0},"s":{"a":0,"k":[100,-100]},"sk":{"a":0,"k":180},"sa":{"a":0,"k":0}}],"np":0},{"ty":"gr","hd":false,"nm":"3 Group","bm":0,"it":[{"ty":"sh","hd":false,"nm":"3","d":1,"ks":{"a":0,"k":{"c":true,"i":[[0,0],[0,0],[0,-1.105],[0,0],[1.105,0],[0,0],[0,1.105],[0,0],[-1.105,0]],"o":[[0,0],[1.105,0],[0,0],[0,1.105],[0,0],[-1.105,0],[0,0],[0,-1.105],[0,0]],"v":[[2,0],[44.547,0],[46.547,2],[46.547,30.659],[44.547,32.659],[2,32.659],[0,30.659],[0,2],[2,0]]}}},{"ty":"fl","hd":false,"bm":0,"c":{"a":1,"k":[{"t":0,"s":[0.424,0.612,0.98],"i":{"x":0.75,"y":0.75},"o":{"x":0.25,"y":0.25}},{"t":75.6,"s":[0.255,0.369,0.588],"i":{"x":0.88,"y":0.77},"o":{"x":0.5,"y":0}},{"t":80.4,"s":[0.424,0.612,0.98],"i":{"x":0,"y":0},"o":{"x":1,"y":1}}]},"r":1,"o":{"a":0,"k":100}},{"ty":"tr","nm":"Transform","a":{"a":0,"k":[0,0]},"o":{"a":0,"k":100},"p":{"a":0,"k":[-23.341,16.33]},"r":{"a":0,"k":0},"s":{"a":0,"k":[100,-100]},"sk":{"a":0,"k":180},"sa":{"a":0,"k":0}}],"np":0},{"ty":"gr","hd":false,"nm":"4 Group","bm":0,"it":[{"ty":"sh","hd":false,"nm":"4","d":1,"ks":{"a":0,"k":{"c":true,"i":[[0,0],[0,0],[0,-1.105],[0,0],[1.105,0],[0,0],[0,1.105],[0,0],[-1.105,0]],"o":[[0,0],[1.105,0],[0,0],[0,1.105],[0,0],[-1.105,0],[0,0],[0,-1.105],[0,0]],"v":[[2,0],[44.547,0],[46.547,2],[46.547,30.659],[44.547,32.659],[2,32.659],[0,30.659],[0,2],[2,0]]}}},{"ty":"fl","hd":false,"bm":0,"c":{"a":1,"k":[{"t":0,"s":[0.424,0.612,0.98],"i":{"x":0.75,"y":0.75},"o":{"x":0.25,"y":0.25}},{"t":80.4,"s":[0.255,0.369,0.588],"i":{"x":0.88,"y":0.77},"o":{"x":0.5,"y":0}},{"t":84.6,"s":[0.424,0.612,0.98],"i":{"x":0,"y":0},"o":{"x":1,"y":1}}]},"r":1,"o":{"a":0,"k":100}},{"ty":"tr","nm":"Transform","a":{"a":0,"k":[0,0]},"o":{"a":0,"k":100},"p":{"a":0,"k":[25.892,16.33]},"r":{"a":0,"k":0},"s":{"a":0,"k":[100,-100]},"sk":{"a":0,"k":180},"sa":{"a":0,"k":0}}],"np":0},{"ty":"gr","hd":false,"nm":"5 Group","bm":0,"it":[{"ty":"sh","hd":false,"nm":"5","d":1,"ks":{"a":0,"k":{"c":false,"i":[[0,0],[9.019,0],[0,0],[0,1.105],[0,0],[-1.105,0],[0,0],[0,-9.018]],"o":[[0,9.019],[0,0],[-1.105,0],[0,0],[0,-1.105],[0,0],[9.019,0],[0,0]],"v":[[370.054,357.422],[353.724,373.752],[327.297,373.752],[325.297,371.752],[325.297,343.093],[327.297,341.093],[353.724,341.093],[370.054,357.422]]}}},{"ty":"fl","hd":false,"bm":0,"c":{"a":0,"k":[0.255,0.369,0.588]},"r":1,"o":{"a":0,"k":100}},{"ty":"tr","nm":"Transform","a":{"a":0,"k":[0,0]},"o":{"a":0,"k":100},"p":{"a":0,"k":[-249.777,-357.422]},"r":{"a":0,"k":0},"s":{"a":0,"k":[100,100]},"sk":{"a":0,"k":0},"sa":{"a":0,"k":0}}],"np":0}]},{"ddd":0,"ind":22,"ty":4,"nm":"원그래프","hd":false,"sr":1,"ks":{"a":{"a":0,"k":[0,0]},"o":{"a":0,"k":100},"p":{"a":0,"k":[250,191.217]},"r":{"a":0,"k":0},"s":{"a":1,"k":[{"t":0,"s":[0,0],"i":{"x":0.15,"y":1.35},"o":{"x":0.15,"y":0.45}},{"t":15,"s":[100,100],"i":{"x":0.75,"y":0.75},"o":{"x":0.25,"y":0.25}},{"t":147,"s":[100,100],"i":{"x":0.5,"y":1},"o":{"x":0.12,"y":0.23}},{"t":153,"s":[0,0],"i":{"x":0,"y":0},"o":{"x":1,"y":1}}]},"sk":{"a":0,"k":0},"sa":{"a":0,"k":0}},"ao":0,"ip":0,"op":181,"st":0,"bm":0,"shapes":[{"ty":"gr","hd":false,"nm":"Oval 1 Group","bm":0,"it":[{"ty":"el","hd":false,"nm":"Oval 1","p":{"a":0,"k":[37.5,37.5]},"s":{"a":0,"k":[75,75]},"d":1},{"ty":"fl","hd":false,"bm":0,"c":{"a":0,"k":[0.769,0.843,0.992]},"r":1,"o":{"a":0,"k":100}},{"ty":"tr","nm":"Transform","a":{"a":0,"k":[37.5,37.5]},"o":{"a":0,"k":100},"p":{"a":0,"k":[-0.113,-0.046]},"r":{"a":0,"k":0},"s":{"a":0,"k":[100,100]},"sk":{"a":0,"k":0},"sa":{"a":0,"k":0}}],"np":0},{"ty":"gr","hd":false,"nm":"Path 1 Group","bm":0,"it":[{"ty":"sh","hd":false,"nm":"Path 1","d":1,"ks":{"a":0,"k":{"c":false,"i":[[0,0],[0.001,-9.615],[0,0],[20.218,0.001],[0,0],[-13.732,-13.73],[-3.679,-8.883]],"o":[[3.68,8.883],[0,0],[-0.001,-20.218],[0,0],[19.418,0.002],[6.799,6.798],[0,0]],"v":[[318.756,157.027],[324.329,185.046],[287.721,185.046],[251.112,148.438],[251.112,111.829],[302.884,133.274],[318.756,157.027]]}}},{"ty":"fl","hd":false,"bm":0,"c":{"a":0,"k":[0.255,0.369,0.588]},"r":1,"o":{"a":0,"k":100}},{"ty":"tr","nm":"Transform","a":{"a":0,"k":[0,0]},"o":{"a":0,"k":100},"p":{"a":0,"k":[-251.113,-185.046]},"r":{"a":0,"k":0},"s":{"a":0,"k":[100,100]},"sk":{"a":0,"k":0},"sa":{"a":0,"k":0}}],"np":0},{"ty":"gr","hd":false,"nm":"Path 1 (2) Group","bm":0,"it":[{"ty":"sh","hd":false,"nm":"Path 1 (2)","d":1,"ks":{"a":0,"k":{"c":false,"i":[[0,0],[-40.436,0],[0,40.437],[40.437,0],[0,-40.437]],"o":[[0,40.437],[40.437,0],[0,-40.437],[-40.437,0],[0,0]],"v":[[177.896,185.046],[251.112,258.263],[324.329,185.046],[251.112,111.829],[177.896,185.046]]}}},{"ty":"sh","hd":false,"nm":"Path 1 (2)","d":1,"ks":{"a":0,"k":{"c":false,"i":[[0,0],[0,20.218],[20.218,0],[0,-20.218],[-20.219,0]],"o":[[20.218,0],[0,-20.218],[-20.219,0],[0,20.218],[0,0]],"v":[[251.114,221.654],[287.722,185.046],[251.114,148.438],[214.505,185.046],[251.114,221.654]]}}},{"ty":"fl","hd":false,"bm":0,"c":{"a":0,"k":[0.424,0.612,0.98]},"r":1,"o":{"a":0,"k":100}},{"ty":"tr","nm":"Transform","a":{"a":0,"k":[0,0]},"o":{"a":0,"k":100},"p":{"a":0,"k":[-251.113,-185.046]},"r":{"a":0,"k":0},"s":{"a":0,"k":[100,100]},"sk":{"a":0,"k":0},"sa":{"a":0,"k":0}}],"np":0}]},{"ddd":0,"ind":26,"ty":4,"nm":"종이","hd":false,"sr":1,"ks":{"a":{"a":0,"k":[0,0]},"o":{"a":0,"k":100},"p":{"a":0,"k":[1.001,0]},"r":{"a":0,"k":0},"s":{"a":0,"k":[100,100]},"sk":{"a":0,"k":0},"sa":{"a":0,"k":0}},"ao":0,"ip":0,"op":181,"st":0,"bm":0,"shapes":[{"ty":"sh","hd":false,"nm":"종이","d":1,"ks":{"a":0,"k":{"c":true,"i":[[0,0],[-2.437,-2.596],[0,0],[0,0],[0,0],[-2.437,-2.596],[0,0],[0,0],[-2.437,-2.596],[0,0],[0,0],[0,0],[-2.437,-2.596],[0,0],[0,0],[0,0],[-2.438,-2.596],[0,0],[0,0],[0,0],[-2.438,-2.596],[0,0],[0,0],[0,0],[-2.438,-2.596],[0,0],[0,0],[-2.438,-2.596],[0,0],[0,0],[0,0],[-2.438,-2.596],[0,0],[0,0],[0,0],[-2.438,-2.596],[0,0],[0,0],[0,0],[-2.438,-2.596],[0,0],[0,0],[0,0],[-2.437,-2.596],[0,0],[0,0],[0,0],[-2.437,-2.596],[0,0],[0,0],[0,0],[-2.437,-2.596],[0,0],[0,0],[-2.444,-2.66],[0,0],[0,0],[0,0],[7.732,0],[0,0],[0,7.732],[0,0],[0,0]],"o":[[2.437,-2.596],[0,0],[0,0],[0,0],[2.438,-2.596],[0,0],[0,0],[2.438,-2.596],[0,0],[0,0],[0,0],[2.438,-2.596],[0,0],[0,0],[0,0],[2.438,-2.596],[0,0],[0,0],[0,0],[2.438,-2.596],[0,0],[0,0],[0,0],[2.438,-2.596],[0,0],[0,0],[2.438,-2.596],[0,0],[0,0],[0,0],[2.437,-2.596],[0,0],[0,0],[0,0],[2.437,-2.596],[0,0],[0,0],[0,0],[2.437,-2.596],[0,0],[0,0],[0,0],[2.437,-2.596],[0,0],[0,0],[0,0],[2.438,-2.596],[0,0],[0,0],[0,0],[2.438,-2.596],[0,0],[0,0],[2.445,-2.66],[0,0],[0,0],[0,0],[0,7.732],[0,0],[-7.732,0],[0,0],[0,0],[0,0]],"v":[[104.497,44.947],[113.526,44.947],[119.221,51],[119.225,51],[124.522,44.948],[133.552,44.948],[139.246,51],[144.544,44.948],[153.574,44.948],[159.268,51],[159.271,51],[164.568,44.948],[173.598,44.948],[179.292,51],[179.295,51],[184.592,44.948],[193.622,44.948],[199.316,51],[199.319,51],[204.616,44.948],[213.646,44.948],[219.34,51],[219.346,51],[224.643,44.948],[233.673,44.948],[239.367,51],[244.664,44.948],[253.694,44.948],[259.388,51],[259.394,51],[264.691,44.948],[273.721,44.948],[279.415,51],[279.418,51],[284.714,44.948],[293.744,44.948],[299.438,51],[299.441,51],[304.737,44.948],[313.767,44.948],[319.461,51],[319.464,51],[324.762,44.948],[333.791,44.948],[339.486,51],[339.491,51],[344.788,44.948],[353.818,44.948],[359.512,51],[359.514,51],[364.811,44.948],[373.841,44.948],[379.474,50.934],[384.456,45.099],[393.574,45.099],[398.998,51],[398.999,51.001],[398.999,423],[384.999,437],[112.999,437],[98.999,423],[98.999,51],[99.001,50.998]]}}},{"ty":"fl","hd":false,"bm":0,"c":{"a":0,"k":[0.769,0.843,0.992]},"r":1,"o":{"a":0,"k":100}}]},{"ddd":0,"ind":27,"ty":4,"nm":"\b입구","hd":false,"sr":1,"ks":{"a":{"a":0,"k":[0,0]},"o":{"a":0,"k":100},"p":{"a":0,"k":[0,0]},"r":{"a":0,"k":0},"s":{"a":0,"k":[100,100]},"sk":{"a":0,"k":0},"sa":{"a":0,"k":0}},"ao":0,"ip":0,"op":181,"st":0,"bm":0,"shapes":[{"ty":"sh","hd":false,"nm":"\b입구","d":1,"ks":{"a":0,"k":{"c":true,"i":[[0,0],[0,0],[0,-14.074],[0,0],[14.074,0],[0,0],[0,14.074],[0,0],[-14.074,0]],"o":[[0,0],[14.074,0],[0,0],[0,14.074],[0,0],[-14.074,0],[0,0],[0,-14.074],[0,0]],"v":[[105.24,408.644],[394.507,408.644],[419.99,434.127],[419.99,434.127],[394.507,459.61],[105.24,459.61],[79.757,434.127],[79.757,434.127],[105.24,408.644]]}}},{"ty":"fl","hd":false,"bm":0,"c":{"a":0,"k":[0.255,0.369,0.588]},"r":1,"o":{"a":0,"k":100}}]}],"meta":{"g":"@phase-software/lottie-exporter 0.7.0"},"nm":"","op":180,"v":"5.6.0","w":500}